[
  {
    "conclusion": "",
    "createdAt": "2026-05-13T04:05:49Z",
    "databaseId": 25777595889,
    "event": "dynamic",
    "headBranch": "main",
    "status": "queued",
    "url": "https://github.com/pfichtner/pfichtner-freetz/actions/runs/25777595889",
    "workflowName": "Dependabot Updates",
    "repository": "pfichtner/pfichtner-freetz"
  },
  {
    "conclusion": "",
    "createdAt": "2026-05-13T04:05:21Z",
    "databaseId": 25777581952,
    "event": "dynamic",
    "headBranch": "main",
    "status": "in_progress",
    "url": "https://github.com/pfichtner/virtualavr/actions/runs/25777581952",
    "workflowName": "Dependabot Updates",
    "repository": "pfichtner/virtualavr"
  },
  {
    "conclusion": "",
    "createdAt": "2026-05-13T04:05:21Z",
    "databaseId": 25777581958,
    "event": "dynamic",
    "headBranch": "main",
    "status": "in_progress",
    "url": "https://github.com/pfichtner/virtualavr/actions/runs/25777581958",
    "workflowName": "Dependabot Updates",
    "repository": "pfichtner/virtualavr"
  },
  {
    "conclusion": "",
    "createdAt": "2026-05-13T04:05:21Z",
    "databaseId": 25777582000,
    "event": "dynamic",
    "headBranch": "main",
    "status": "in_progress",
    "url": "https://github.com/pfichtner/virtualavr/actions/runs/25777582000",
    "workflowName": "Dependabot Updates",
    "repository": "pfichtner/virtualavr"
  },
  {
    "conclusion": "success",
    "createdAt": "2026-05-13T04:04:20Z",
    "databaseId": 25777549826,
    "event": "dynamic",
    "headBranch": "main",
    "status": "completed",
    "url": "https://github.com/pfichtner/log4shell-hunter/actions/runs/25777549826",
    "workflowName": "Dependabot Updates",
    "repository": "pfichtner/log4shell-hunter"
  },
  {
    "conclusion": "success",
    "createdAt": "2026-05-13T04:04:20Z",
    "databaseId": 25777549861,
    "event": "dynamic",
    "headBranch": "main",
    "status": "completed",
    "url": "https://github.com/pfichtner/log4shell-hunter/actions/runs/25777549861",
    "workflowName": "Dependabot Updates",
    "repository": "pfichtner/log4shell-hunter"
  },
  {
    "conclusion": "success",
    "createdAt": "2026-05-13T04:03:53Z",
    "databaseId": 25777535151,
    "event": "dynamic",
    "headBranch": "main",
    "status": "completed",
    "url": "https://github.com/pfichtner/testtypes/actions/runs/25777535151",
    "workflowName": "Dependabot Updates",
    "repository": "pfichtner/testtypes"
  },
  {
    "conclusion": "success",
    "createdAt": "2026-05-13T04:03:53Z",
    "databaseId": 25777535189,
    "event": "dynamic",
    "headBranch": "main",
    "status": "completed",
    "url": "https://github.com/pfichtner/testtypes/actions/runs/25777535189",
    "workflowName": "Dependabot Updates",
    "repository": "pfichtner/testtypes"
  },
  {
    "conclusion": "success",
    "createdAt": "2026-05-13T03:26:26Z",
    "databaseId": 25776387022,
    "event": "pull_request",
    "headBranch": "dependabot/maven/org.slf4j-slf4j-api-2.0.18",
    "status": "completed",
    "url": "https://github.com/pfichtner/vaadoo/actions/runs/25776387022",
    "workflowName": "Java CI with Maven",
    "repository": "pfichtner/vaadoo"
  },
  {
    "conclusion": "success",
    "createdAt": "2026-05-13T03:26:24Z",
    "databaseId": 25776385632,
    "event": "push",
    "headBranch": "dependabot/maven/org.slf4j-slf4j-api-2.0.18",
    "status": "completed",
    "url": "https://github.com/pfichtner/vaadoo/actions/runs/25776385632",
    "workflowName": "Java CI with Maven",
    "repository": "pfichtner/vaadoo"
  },
  {
    "conclusion": "success",
    "createdAt": "2026-05-13T03:25:41Z",
    "databaseId": 25776363962,
    "event": "dynamic",
    "headBranch": "main",
    "status": "completed",
    "url": "https://github.com/pfichtner/vaadoo/actions/runs/25776363962",
    "workflowName": "Dependabot Updates",
    "repository": "pfichtner/vaadoo"
  },
  {
    "conclusion": "success",
    "createdAt": "2026-05-13T03:25:41Z",
    "databaseId": 25776363965,
    "event": "dynamic",
    "headBranch": "main",
    "status": "completed",
    "url": "https://github.com/pfichtner/vaadoo/actions/runs/25776363965",
    "workflowName": "Dependabot Updates",
    "repository": "pfichtner/vaadoo"
  },
  {
    "conclusion": "success",
    "createdAt": "2026-05-12T09:59:55Z",
    "databaseId": 25727329367,
    "event": "schedule",
    "headBranch": "main",
    "status": "completed",
    "url": "https://github.com/pfichtner/log4shell-hunter/actions/runs/25727329367",
    "workflowName": "Scorecard supply-chain security",
    "repository": "pfichtner/log4shell-hunter"
  },
  {
    "conclusion": "success",
    "createdAt": "2026-05-12T09:52:56Z",
    "databaseId": 25726982604,
    "event": "dynamic",
    "headBranch": "main",
    "status": "completed",
    "url": "https://github.com/pfichtner/pfichtner-freetz-vagrantbox/actions/runs/25726982604",
    "workflowName": "Dependabot Updates",
    "repository": "pfichtner/pfichtner-freetz-vagrantbox"
  },
  {
    "conclusion": "success",
    "createdAt": "2026-05-12T09:52:56Z",
    "databaseId": 25726982289,
    "event": "dynamic",
    "headBranch": "main",
    "status": "completed",
    "url": "https://github.com/pfichtner/pacto/actions/runs/25726982289",
    "workflowName": "Dependabot Updates",
    "repository": "pfichtner/pacto"
  },
  {
    "conclusion": "success",
    "createdAt": "2026-05-12T09:52:56Z",
    "databaseId": 25726982328,
    "event": "dynamic",
    "headBranch": "main",
    "status": "completed",
    "url": "https://github.com/pfichtner/pacto/actions/runs/25726982328",
    "workflowName": "Dependabot Updates",
    "repository": "pfichtner/pacto"
  },
  {
    "conclusion": "success",
    "createdAt": "2026-05-12T08:50:23Z",
    "databaseId": 25723887798,
    "event": "dynamic",
    "headBranch": "main",
    "status": "completed",
    "url": "https://github.com/pfichtner/jsipdialer/actions/runs/25723887798",
    "workflowName": "Dependabot Updates",
    "repository": "pfichtner/jsipdialer"
  },
  {
    "conclusion": "success",
    "createdAt": "2026-05-12T08:50:18Z",
    "databaseId": 25723884025,
    "event": "dynamic",
    "headBranch": "main",
    "status": "completed",
    "url": "https://github.com/pfichtner/jsipdialer/actions/runs/25723884025",
    "workflowName": "Dependabot Updates",
    "repository": "pfichtner/jsipdialer"
  },
  {
    "conclusion": "success",
    "createdAt": "2026-05-12T08:45:21Z",
    "databaseId": 25723642481,
    "event": "dynamic",
    "headBranch": "main",
    "status": "completed",
    "url": "https://github.com/pfichtner/mqtt-machine-state/actions/runs/25723642481",
    "workflowName": "Dependabot Updates",
    "repository": "pfichtner/mqtt-machine-state"
  },
  {
    "conclusion": "success",
    "createdAt": "2026-05-12T08:45:21Z",
    "databaseId": 25723642489,
    "event": "dynamic",
    "headBranch": "main",
    "status": "completed",
    "url": "https://github.com/pfichtner/mqtt-machine-state/actions/runs/25723642489",
    "workflowName": "Dependabot Updates",
    "repository": "pfichtner/mqtt-machine-state"
  },
  {
    "conclusion": "success",
    "createdAt": "2026-05-12T08:40:48Z",
    "databaseId": 25723419562,
    "event": "dynamic",
    "headBranch": "main",
    "status": "completed",
    "url": "https://github.com/pfichtner/mockapproval/actions/runs/25723419562",
    "workflowName": "Dependabot Updates",
    "repository": "pfichtner/mockapproval"
  },
  {
    "conclusion": "success",
    "createdAt": "2026-05-12T08:40:47Z",
    "databaseId": 25723419395,
    "event": "dynamic",
    "headBranch": "main",
    "status": "completed",
    "url": "https://github.com/pfichtner/mockapproval/actions/runs/25723419395",
    "workflowName": "Dependabot Updates",
    "repository": "pfichtner/mockapproval"
  },
  {
    "conclusion": "success",
    "createdAt": "2026-05-12T08:39:37Z",
    "databaseId": 25723361784,
    "event": "dynamic",
    "headBranch": "main",
    "status": "completed",
    "url": "https://github.com/pfichtner/pfichtner-freetz/actions/runs/25723361784",
    "workflowName": "Dependabot Updates",
    "repository": "pfichtner/pfichtner-freetz"
  },
  {
    "conclusion": "success",
    "createdAt": "2026-05-12T08:39:05Z",
    "databaseId": 25723336008,
    "event": "dynamic",
    "headBranch": "main",
    "status": "completed",
    "url": "https://github.com/pfichtner/virtualavr/actions/runs/25723336008",
    "workflowName": "Dependabot Updates",
    "repository": "pfichtner/virtualavr"
  },
  {
    "conclusion": "success",
    "createdAt": "2026-05-12T08:39:04Z",
    "databaseId": 25723335182,
    "event": "dynamic",
    "headBranch": "main",
    "status": "completed",
    "url": "https://github.com/pfichtner/virtualavr/actions/runs/25723335182",
    "workflowName": "Dependabot Updates",
    "repository": "pfichtner/virtualavr"
  },
  {
    "conclusion": "success",
    "createdAt": "2026-05-12T08:37:56Z",
    "databaseId": 25723280287,
    "event": "dynamic",
    "headBranch": "main",
    "status": "completed",
    "url": "https://github.com/pfichtner/log4shell-hunter/actions/runs/25723280287",
    "workflowName": "Dependabot Updates",
    "repository": "pfichtner/log4shell-hunter"
  },
  {
    "conclusion": "success",
    "createdAt": "2026-05-12T08:37:51Z",
    "databaseId": 25723276195,
    "event": "dynamic",
    "headBranch": "main",
    "status": "completed",
    "url": "https://github.com/pfichtner/log4shell-hunter/actions/runs/25723276195",
    "workflowName": "Dependabot Updates",
    "repository": "pfichtner/log4shell-hunter"
  },
  {
    "conclusion": "success",
    "createdAt": "2026-05-12T08:37:12Z",
    "databaseId": 25723244572,
    "event": "dynamic",
    "headBranch": "main",
    "status": "completed",
    "url": "https://github.com/pfichtner/testtypes/actions/runs/25723244572",
    "workflowName": "Dependabot Updates",
    "repository": "pfichtner/testtypes"
  },
  {
    "conclusion": "success",
    "createdAt": "2026-05-12T08:37:12Z",
    "databaseId": 25723244579,
    "event": "dynamic",
    "headBranch": "main",
    "status": "completed",
    "url": "https://github.com/pfichtner/testtypes/actions/runs/25723244579",
    "workflowName": "Dependabot Updates",
    "repository": "pfichtner/testtypes"
  },
  {
    "conclusion": "success",
    "createdAt": "2026-05-12T08:13:16Z",
    "databaseId": 25722104138,
    "event": "dynamic",
    "headBranch": "main",
    "status": "completed",
    "url": "https://github.com/pfichtner/vaadoo/actions/runs/25722104138",
    "workflowName": "Dependabot Updates",
    "repository": "pfichtner/vaadoo"
  },
  {
    "conclusion": "success",
    "createdAt": "2026-05-12T06:50:45Z",
    "databaseId": 25718438919,
    "event": "workflow_dispatch",
    "headBranch": "main",
    "status": "completed",
    "url": "https://github.com/pfichtner/pfichtner-freetz/actions/runs/25718438919",
    "workflowName": "Update Freetz-NG Prerequisites",
    "repository": "pfichtner/pfichtner-freetz"
  },
  {
    "conclusion": "failure",
    "createdAt": "2026-05-12T06:29:25Z",
    "databaseId": 25717584263,
    "event": "schedule",
    "headBranch": "main",
    "status": "completed",
    "url": "https://github.com/pfichtner/pfichtner-freetz/actions/runs/25717584263",
    "workflowName": "Update Freetz-NG Prerequisites",
    "repository": "pfichtner/pfichtner-freetz"
  },
  {
    "conclusion": "success",
    "createdAt": "2026-05-12T05:47:47Z",
    "databaseId": 25716030196,
    "event": "schedule",
    "headBranch": "main",
    "status": "completed",
    "url": "https://github.com/pfichtner/testtypes/actions/runs/25716030196",
    "workflowName": "Scorecard supply-chain security",
    "repository": "pfichtner/testtypes"
  },
  {
    "conclusion": "success",
    "createdAt": "2026-05-11T06:56:22Z",
    "databaseId": 25655119729,
    "event": "schedule",
    "headBranch": "main",
    "status": "completed",
    "url": "https://github.com/pfichtner/pfichtner-freetz/actions/runs/25655119729",
    "workflowName": "Update Freetz-NG Prerequisites",
    "repository": "pfichtner/pfichtner-freetz"
  },
  {
    "conclusion": "success",
    "createdAt": "2026-05-11T05:25:41Z",
    "databaseId": 25652000899,
    "event": "dynamic",
    "headBranch": "main",
    "status": "completed",
    "url": "https://github.com/pfichtner/pfichtner-freetz-vagrantbox/actions/runs/25652000899",
    "workflowName": "Dependabot Updates",
    "repository": "pfichtner/pfichtner-freetz-vagrantbox"
  },
  {
    "conclusion": "success",
    "createdAt": "2026-05-11T05:25:40Z",
    "databaseId": 25652000441,
    "event": "dynamic",
    "headBranch": "main",
    "status": "completed",
    "url": "https://github.com/pfichtner/pacto/actions/runs/25652000441",
    "workflowName": "Dependabot Updates",
    "repository": "pfichtner/pacto"
  },
  {
    "conclusion": "success",
    "createdAt": "2026-05-11T05:25:40Z",
    "databaseId": 25652000480,
    "event": "dynamic",
    "headBranch": "main",
    "status": "completed",
    "url": "https://github.com/pfichtner/pacto/actions/runs/25652000480",
    "workflowName": "Dependabot Updates",
    "repository": "pfichtner/pacto"
  },
  {
    "conclusion": "success",
    "createdAt": "2026-05-11T04:18:13Z",
    "databaseId": 25650027729,
    "event": "dynamic",
    "headBranch": "main",
    "status": "completed",
    "url": "https://github.com/pfichtner/jsipdialer/actions/runs/25650027729",
    "workflowName": "Dependabot Updates",
    "repository": "pfichtner/jsipdialer"
  },
  {
    "conclusion": "success",
    "createdAt": "2026-05-11T04:18:13Z",
    "databaseId": 25650027740,
    "event": "dynamic",
    "headBranch": "main",
    "status": "completed",
    "url": "https://github.com/pfichtner/jsipdialer/actions/runs/25650027740",
    "workflowName": "Dependabot Updates",
    "repository": "pfichtner/jsipdialer"
  },
  {
    "conclusion": "success",
    "createdAt": "2026-05-11T04:13:34Z",
    "databaseId": 25649908125,
    "event": "dynamic",
    "headBranch": "main",
    "status": "completed",
    "url": "https://github.com/pfichtner/mqtt-machine-state/actions/runs/25649908125",
    "workflowName": "Dependabot Updates",
    "repository": "pfichtner/mqtt-machine-state"
  },
  {
    "conclusion": "success",
    "createdAt": "2026-05-11T04:13:34Z",
    "databaseId": 25649908385,
    "event": "dynamic",
    "headBranch": "main",
    "status": "completed",
    "url": "https://github.com/pfichtner/mqtt-machine-state/actions/runs/25649908385",
    "workflowName": "Dependabot Updates",
    "repository": "pfichtner/mqtt-machine-state"
  },
  {
    "conclusion": "success",
    "createdAt": "2026-05-11T04:08:48Z",
    "databaseId": 25649786297,
    "event": "dynamic",
    "headBranch": "main",
    "status": "completed",
    "url": "https://github.com/pfichtner/mockapproval/actions/runs/25649786297",
    "workflowName": "Dependabot Updates",
    "repository": "pfichtner/mockapproval"
  },
  {
    "conclusion": "success",
    "createdAt": "2026-05-11T04:08:48Z",
    "databaseId": 25649786334,
    "event": "dynamic",
    "headBranch": "main",
    "status": "completed",
    "url": "https://github.com/pfichtner/mockapproval/actions/runs/25649786334",
    "workflowName": "Dependabot Updates",
    "repository": "pfichtner/mockapproval"
  },
  {
    "conclusion": "success",
    "createdAt": "2026-05-11T02:32:37Z",
    "databaseId": 25647253386,
    "event": "schedule",
    "headBranch": "main",
    "status": "completed",
    "url": "https://github.com/pfichtner/mqtt-machine-state/actions/runs/25647253386",
    "workflowName": "CodeQL",
    "repository": "pfichtner/mqtt-machine-state"
  }
]
